imgw_api_wrapper/__init__.py
imgw_api_wrapper/imgw.py
imgw_api_wrapper-0.2.1.dist-info/METADATA
imgw_api_wrapper-0.2.1.dist-info/WHEEL
imgw_api_wrapper-0.2.1.dist-info/licenses/LICENSE
imgw_api_wrapper-0.2.1.dist-info/RECORD
