Metadata-Version: 2.1
Name: imgw_api_wrapper
Version: 0.2.1
Summary: IMGW (Polish weather service) API wrapper. Do not use for commercial purposes.
Project-URL: Homepage, https://github.com/crazyjerz/imgw_api_wrapper
Author-email: crazyjerz <informatyka11111@wp.pl>
License-File: LICENSE
Classifier: License :: OSI Approved :: MIT License
Classifier: Operating System :: OS Independent
Classifier: Programming Language :: Python :: 3
Requires-Python: >=3.7
